{
  "publicPath": "/_nuxt/",
  "all": [
    "../server/index.spa.html",
    "../server/index.ssr.html",
    "1d613b1.js",
    "3ef24b0.js",
    "5419493.js",
    "602ec53.js",
    "64c7e35.js",
    "7a10f93.js",
    "8d7b133.js",
    "92ef6ba.js",
    "9905b3a.js",
    "LICENSES",
    "a9cc809.js",
    "be872fb.js",
    "c651816.js",
    "d82fd89.js",
    "d9ca980.js",
    "e5fa833.js",
    "f5cfd8c.js",
    "img/profile_image.ea3c4f5.png"
  ],
  "initial": [
    "d82fd89.js",
    "602ec53.js",
    "92ef6ba.js",
    "8d7b133.js"
  ],
  "async": [
    "1d613b1.js",
    "3ef24b0.js",
    "5419493.js",
    "64c7e35.js",
    "7a10f93.js",
    "9905b3a.js",
    "a9cc809.js",
    "be872fb.js",
    "c651816.js",
    "d9ca980.js",
    "e5fa833.js",
    "f5cfd8c.js"
  ],
  "modules": {
    "34412188": [
      8
    ],
    "45415706": [
      8
    ],
    "46023767": [
      8
    ],
    "63565697": [
      5
    ],
    "76ccd660": [
      5
    ],
    "dcf8516c": [
      8
    ],
    "21824f6c": [
      5
    ],
    "6859470d": [
      5
    ],
    "1f74a51d": [
      5
    ],
    "11feec0e": [
      5
    ],
    "4b3f1f0b": [
      5
    ],
    "4a2adfb6": [
      5
    ],
    "212358ae": [
      5
    ],
    "6ad2326f": [
      5
    ],
    "e1004cfe": [
      5
    ],
    "7e3d9315": [
      5
    ],
    "67854f8b": [
      5
    ],
    "076af08a": [
      5
    ],
    "de5249a8": [
      5
    ],
    "1e7587d8": [
      5
    ],
    "67f0fdc6": [
      5
    ],
    "930aa160": [
      5
    ],
    "b24166a2": [
      5
    ],
    "36adc394": [
      5
    ],
    "2bd9bf36": [
      5
    ],
    "4d309eec": [
      5
    ],
    "5c152832": [
      5
    ],
    "a771261c": [
      5
    ],
    "62264ed6": [
      5
    ],
    "3def9c57": [
      5
    ],
    "894b178a": [
      5
    ],
    "2936c35a": [
      5
    ],
    "1c4b0558": [
      5
    ],
    "23b3b734": [
      5
    ],
    "5790eae8": [
      9
    ],
    "9e96bbf4": [
      9
    ],
    "53cbdc42": [
      9
    ],
    "0f1ce861": [
      5
    ],
    "dc33a986": [
      5
    ],
    "8f71aa76": [
      5
    ],
    "bf84de24": [
      5
    ],
    "04a92dd3": [
      5
    ],
    "6ca7bf89": [
      8
    ],
    "628e2eea": [
      8
    ],
    "b6b0b160": [
      8
    ],
    "8278d8ce": [
      8
    ],
    "603cb4bf": [
      8
    ],
    "474e3cfa": [
      8
    ],
    "13df5fcf": [
      8
    ],
    "82efa5ee": [
      8
    ],
    "5ffeabcb": [
      8
    ],
    "6798a158": [
      8
    ],
    "47af8965": [
      8
    ],
    "13c449cb": [
      8
    ],
    "4af874d2": [
      8
    ],
    "7a353568": [
      8
    ],
    "35f18a4a": [
      8
    ],
    "daf7e2e6": [
      8
    ],
    "71e5f75b": [
      8
    ],
    "2fb0f05b": [
      8
    ],
    "a1beb3a4": [
      8
    ],
    "9cfbc794": [
      8
    ],
    "557346ce": [
      8
    ],
    "303499da": [
      8
    ],
    "425c32a7": [
      8
    ],
    "4f3d072e": [
      8
    ],
    "df09d84e": [
      8
    ],
    "077d7cdf": [
      8
    ],
    "192d8194": [
      8
    ],
    "b63bbfde": [
      8
    ],
    "5a912444": [
      5
    ],
    "fae35d18": [
      5
    ],
    "00b4b012": [
      5
    ],
    "ae53fe66": [
      5
    ],
    "681c61e0": [
      5
    ],
    "5cbcde2e": [
      5
    ],
    "b5a7e0b6": [
      5
    ],
    "5a2e5d7f": [
      5
    ],
    "a5c574d6": [
      5
    ],
    "1754d969": [
      5
    ],
    "3f7cb5ac": [
      5
    ],
    "7d9aad2e": [
      5
    ],
    "44962fd0": [
      5
    ],
    "60018c2f": [
      8
    ],
    "e122afb8": [
      5
    ],
    "421f56c6": [
      5
    ],
    "51a47e3b": [
      5
    ],
    "7512a56c": [
      5
    ],
    "265e8704": [
      5
    ],
    "0d74d898": [
      5
    ],
    "c9c9436e": [
      5
    ],
    "7add4223": [
      5
    ],
    "3e2d0410": [
      5
    ],
    "16bf1b2d": [
      9
    ],
    "7d6c7b58": [
      9
    ],
    "62b32565": [
      5
    ],
    "1c8b0c49": [
      5
    ],
    "3b057c26": [
      5
    ],
    "e8a3d3c2": [
      5
    ],
    "5e537db0": [
      5
    ],
    "370af526": [
      5
    ],
    "4b6208ba": [
      5
    ],
    "0d9a1fc9": [
      5
    ],
    "723aca28": [
      5
    ],
    "6a03a418": [
      5
    ],
    "c49d894e": [
      5
    ],
    "1f863426": [
      5
    ],
    "10f96db6": [
      5
    ],
    "4870f8ab": [
      5
    ],
    "69ef36c9": [
      5
    ],
    "abdfa5ca": [
      5
    ],
    "695e0b52": [
      5
    ],
    "54b6b012": [
      5
    ],
    "48fddcac": [
      5
    ],
    "34e28cb6": [
      5
    ],
    "12c7a200": [
      5
    ],
    "1b9ad8dc": [
      5
    ],
    "4280b3a5": [
      5
    ],
    "0016b4a4": [
      5
    ],
    "886b8a0e": [
      5
    ],
    "1304a5da": [
      5
    ],
    "df365cf4": [
      5
    ],
    "5331b0ec": [
      9
    ],
    "627512d0": [
      5
    ],
    "3c73f968": [
      5
    ],
    "639920ba": [
      5
    ],
    "63b28f9b": [
      5
    ],
    "763fae16": [
      5
    ],
    "10f1bd8d": [
      8
    ],
    "794bfcd7": [
      5
    ],
    "ef576140": [
      5
    ],
    "be448f44": [
      5
    ],
    "0b065f9e": [
      5
    ],
    "f948961c": [
      5
    ],
    "6ea2502c": [
      5
    ],
    "13a3d672": [
      5
    ],
    "075e269e": [
      5
    ],
    "7b6506d6": [
      5
    ],
    "0b8b4fdf": [
      5
    ],
    "44bb4d52": [
      5
    ],
    "238a6d40": [
      5
    ],
    "1c246c82": [
      5
    ],
    "dbb23308": [
      5
    ],
    "781b379f": [
      5
    ],
    "2a56461a": [
      5
    ],
    "57dec6d3": [
      5
    ],
    "5ec7e0ce": [
      5
    ],
    "a7e60d36": [
      5
    ],
    "1e01a7b4": [
      5
    ],
    "89a63e5e": [
      5
    ],
    "3089cdbc": [
      5
    ],
    "25239f34": [
      5
    ],
    "1e68f98a": [
      5
    ],
    "b7d1fd86": [
      5
    ],
    "23b059ae": [
      5
    ],
    "4b852cbf": [
      5
    ],
    "a7b36450": [
      5
    ],
    "5b34024c": [
      9
    ],
    "13c08508": [
      9
    ],
    "e0207428": [
      9
    ],
    "7459443f": [
      9
    ],
    "5ff763fe": [
      8
    ],
    "0e7bddaa": [
      9
    ],
    "6601e926": [
      5
    ],
    "89a4ae14": [
      9
    ],
    "d3142a4c": [
      9
    ],
    "c8798d7e": [
      8
    ],
    "796cbd22": [
      5
    ],
    "2267c2c9": [
      5
    ],
    "ee084e20": [
      5
    ],
    "2e7af3a5": [
      5
    ],
    "618898ca": [
      5
    ],
    "51b69278": [
      5
    ],
    "2caaf6fe": [
      5
    ],
    "49ddb42c": [
      5
    ],
    "98a5a07c": [
      5
    ],
    "00438c27": [
      5
    ],
    "5cfaab77": [
      5
    ],
    "02aa8cf0": [
      5
    ],
    "1206b289": [
      5
    ],
    "48151a55": [
      5
    ],
    "0615ae55": [
      5
    ],
    "36eda2de": [
      5
    ],
    "261d13a4": [
      5
    ],
    "172b4b22": [
      5
    ],
    "75577ace": [
      5
    ],
    "983b9c72": [
      5
    ],
    "b0cfbf64": [
      5
    ],
    "28de0ec4": [
      5
    ],
    "3fc9ed06": [
      5
    ],
    "ba70338a": [
      5
    ],
    "72e0e139": [
      5
    ],
    "53a9fcf4": [
      5
    ],
    "5d28802e": [
      5
    ],
    "30f9ebd1": [
      5
    ],
    "337540f8": [
      5
    ],
    "72b5454c": [
      5
    ],
    "3474798c": [
      5
    ],
    "39674d96": [
      5
    ],
    "f9a52280": [
      5
    ],
    "541725c7": [
      5
    ],
    "3675dbe9": [
      8
    ],
    "3d271616": [
      8
    ],
    "1ea4f1e4": [
      8
    ],
    "7eb19804": [
      8
    ],
    "2424befc": [
      8
    ],
    "7b8b2e50": [
      8
    ],
    "759947f6": [
      8
    ],
    "a0b20300": [
      8
    ],
    "3fec7e92": [
      9
    ],
    "01d165e7": [
      5
    ],
    "1d7f9d03": [
      5
    ],
    "1d5d5ce7": [
      5
    ],
    "ee68ce88": [
      5
    ],
    "4ff65777": [
      5
    ],
    "3718505c": [
      5
    ],
    "c60f5438": [
      5
    ],
    "5ab5d05e": [
      5
    ],
    "e55986d0": [
      5
    ],
    "5d8c58cd": [
      9
    ],
    "2c13ef30": [
      9
    ],
    "0f047d04": [
      9
    ],
    "26d27cf7": [
      9
    ],
    "14d6a6bb": [
      9
    ],
    "595cb202": [
      9
    ],
    "490ce51a": [
      9
    ],
    "46105ef6": [
      9
    ],
    "fbd4695e": [
      9
    ],
    "42afb0a2": [
      9
    ],
    "2e026a6e": [
      9
    ],
    "9122cf98": [
      5
    ],
    "66b081cb": [
      9
    ],
    "dafe9408": [
      9
    ],
    "99d08978": [
      9
    ],
    "a4ea65a4": [
      8
    ],
    "1fff2a9f": [
      8
    ],
    "53a2cdc4": [
      9
    ],
    "4f03ccbf": [
      8
    ],
    "1f6ed7da": [
      8
    ],
    "015e50b0": [
      5
    ],
    "a4d880ca": [
      5
    ],
    "6dc13934": [
      5
    ],
    "69d95103": [
      8
    ],
    "6776efd2": [
      9
    ],
    "31f729b0": [
      8
    ],
    "c5396a5e": [
      5
    ],
    "e698287a": [
      5
    ],
    "da46ef78": [
      5
    ],
    "9cd49cb2": [
      5
    ],
    "28d43dee": [
      5
    ],
    "71c76656": [
      5
    ],
    "cc11b298": [
      5
    ],
    "747134c5": [
      5
    ],
    "42f5e6d1": [
      5
    ],
    "f51b29fe": [
      5
    ],
    "7b668a6d": [
      5
    ],
    "07383684": [
      5
    ],
    "8d5f32da": [
      5
    ],
    "c2c14cbe": [
      5
    ],
    "27b6ddab": [
      5
    ],
    "298a32f2": [
      5
    ],
    "b8e2be48": [
      5
    ],
    "c8631a0e": [
      5
    ],
    "3f8813cc": [
      5
    ],
    "673f7596": [
      5
    ],
    "65a47d51": [
      5
    ],
    "b9306e8e": [
      5
    ],
    "1b114df7": [
      5
    ],
    "ca257d88": [
      5
    ],
    "eddefc24": [
      5
    ],
    "07b5ac35": [
      5
    ],
    "43b9fe28": [
      5
    ],
    "5ec1ef26": [
      5
    ],
    "36dffd2c": [
      5
    ],
    "75b215bb": [
      5
    ],
    "14f51e3f": [
      5
    ],
    "17ac458c": [
      5
    ],
    "bab0effe": [
      8
    ],
    "29333ea5": [
      8
    ],
    "07e37b0d": [
      8
    ],
    "1a5c18b1": [
      8
    ],
    "3e2f664c": [
      8
    ],
    "2bac7a08": [
      8
    ],
    "dc7953bc": [
      9
    ],
    "32f59e44": [
      9
    ],
    "c1f97102": [
      8
    ],
    "1d90d423": [
      8
    ],
    "5ddada68": [
      8
    ],
    "38563fa8": [
      8
    ],
    "19eab3b6": [
      8
    ],
    "bd07f7f8": [
      8
    ],
    "fd966698": [
      8
    ],
    "00255158": [
      8
    ],
    "5662a3f0": [
      8
    ],
    "428aa10d": [
      8
    ],
    "224369bd": [
      8
    ],
    "08ea7e38": [
      8
    ],
    "516c1d46": [
      9
    ],
    "a59c60be": [
      9
    ],
    "5c8d729c": [
      9
    ],
    "c320df9c": [
      9
    ],
    "3052b342": [
      9
    ],
    "3e48424b": [
      9
    ],
    "b0410040": [
      9
    ],
    "431c07e4": [
      9
    ],
    "0b13c370": [
      9
    ],
    "18d7934b": [
      8
    ],
    "09754116": [
      9
    ],
    "5d0afeca": [
      5
    ],
    "772a9ae8": [
      5
    ],
    "58e0b568": [
      5
    ],
    "1093e169": [
      5
    ],
    "768449f0": [
      5
    ],
    "127d5d76": [
      5
    ],
    "081b46b6": [
      5
    ],
    "f227ce54": [
      5
    ],
    "3b5a849b": [
      5
    ],
    "6b028cdc": [
      5
    ],
    "d61fa8c8": [
      5
    ],
    "6bd8c267": [
      5
    ],
    "c8c77fde": [
      5
    ],
    "48b1a3f9": [
      5
    ],
    "1c9d2fe4": [
      5
    ],
    "5adbe5b1": [
      5
    ],
    "67d79670": [
      5
    ],
    "239b8c12": [
      5
    ],
    "e47d6e60": [
      5
    ],
    "89f42c10": [
      5
    ],
    "6f5778d7": [
      9
    ],
    "52c4aeaa": [
      9
    ],
    "549ad5cd": [
      9
    ],
    "5043cd48": [
      9
    ],
    "69740cdc": [
      9
    ],
    "1a5fafee": [
      9
    ],
    "7eb2a9b3": [
      8
    ],
    "c5810e00": [
      8
    ],
    "aa3cc1fa": [
      8
    ],
    "2f835d5a": [
      8
    ],
    "22aef06a": [
      8
    ],
    "1c01efea": [
      8
    ],
    "8a495b16": [
      8
    ],
    "e616fd2e": [
      8
    ],
    "824abb4a": [
      8
    ],
    "23c95fa1": [
      8
    ],
    "2a66de10": [
      8
    ],
    "73ef8679": [
      8
    ],
    "696ad648": [
      8
    ],
    "4f2d97df": [
      8
    ],
    "409cbdd8": [
      8
    ],
    "489f816c": [
      8
    ],
    "034ee569": [
      8
    ],
    "61ba9f0a": [
      8
    ],
    "074e354f": [
      8
    ],
    "0ee1057c": [
      8
    ],
    "1bba9cf0": [
      8
    ],
    "336bd05c": [
      8
    ],
    "03376fe4": [
      8
    ],
    "7cefad90": [
      8
    ],
    "179e7c1c": [
      8
    ],
    "744662c7": [
      8
    ],
    "1d454710": [
      8
    ],
    "42ba846f": [
      8
    ],
    "cda0182c": [
      8
    ],
    "f2fd2592": [
      8
    ],
    "171396f4": [
      8
    ],
    "0628d805": [
      8
    ],
    "7d6f4ac0": [
      8
    ],
    "0a2827eb": [
      8
    ],
    "581d38d8": [
      8
    ],
    "03e4b49a": [
      16
    ],
    "6a091546": [
      10
    ],
    "031bfcaf": [
      2
    ],
    "4f65bf36": [
      10
    ],
    "01b62d15": [
      10
    ],
    "5b41e092": [
      2
    ],
    "94cde732": [
      2
    ],
    "acab75ca": [
      3,
      17
    ],
    "c93dd0b6": [
      17
    ],
    "ea5ad60a": [
      17
    ],
    "5b1320e7": [
      17
    ],
    "61320eec": [
      17
    ],
    "799dd536": [
      17
    ],
    "b7b2516e": [
      17
    ],
    "69814e42": [
      17
    ],
    "59aa6b66": [
      17
    ],
    "67e024c1": [
      3,
      17
    ],
    "0fbf440d": [
      10
    ],
    "bf148960": [
      10
    ],
    "81c2aab2": [
      10
    ],
    "025e5136": [
      10
    ],
    "801d7e42": [
      10
    ],
    "40b42b67": [
      4,
      19
    ],
    "6e33317f": [
      4,
      19
    ],
    "366164cd": [
      4,
      19
    ],
    "2ac66236": [
      4,
      19
    ],
    "4ce74d05": [
      4,
      19
    ],
    "1204ac11": [
      2
    ],
    "5387dc9a": [
      2
    ],
    "567bd223": [
      2
    ],
    "5da6a080": [
      2
    ],
    "8e057f4a": [
      2
    ]
  },
  "assetsMapping": {
    "56882011": [
      "a9cc809.js"
    ],
    "31d939e4": [
      "1d613b1.js"
    ],
    "be5ea2d0": [
      "3ef24b0.js"
    ],
    "2a130dde": [
      "5419493.js"
    ],
    "085a35c4": [
      "602ec53.js"
    ],
    "d24360d4": [
      "64c7e35.js"
    ],
    "2f009d76": [
      "7a10f93.js"
    ],
    "1a3ae26b": [
      "8d7b133.js"
    ],
    "7ea24c87": [
      "92ef6ba.js"
    ],
    "587dc592": [
      "9905b3a.js"
    ],
    "345b3f52": [
      "be872fb.js"
    ],
    "54ed0fa4": [
      "c651816.js"
    ],
    "6fca0322": [
      "d82fd89.js"
    ],
    "bba68bf6": [
      "d9ca980.js"
    ],
    "72f637b4": [
      "e5fa833.js"
    ],
    "345a32f6": [
      "f5cfd8c.js"
    ]
  }
}